{
  "Arizona Cardinals": {
    "Att": 22,
    "Rec": 33,
    "Rec Yds": 357,
    "Rec TD": 1,
    "Rush RZ In20": 2,
    "Rush RZ In5": 1,
    "Tar RZ In5": 1,
    "Fantasy Pts/G": 80.7,
    "Rush RZ In10": 2,
    "Tar RZ In20": 6,
    "Fantasy Pts": 81,
    "RZ Opp In5": 2,
    "Rush Yds": 51,
    "url": "https://www.rotowire.com/football/redzonestats.htm?pos=TM&season=2017&range=Week4",
    "Tar RZ In10": 2,
    "Rush TD": 0,
    "RZ Opp In20": 8,
    "Col Teamname": "Arizona Cardinals",
    "RZ Opp In10": 4
  },
  "Atlanta Falcons": {
    "Att": 29,
    "Rec": 24,
    "Rec Yds": 242,
    "Rec TD": 1,
    "Rush RZ In20": 6,
    "Rush RZ In5": 3,
    "Tar RZ In5": 2,
    "Fantasy Pts/G": 72,
    "Rush RZ In10": 5,
    "Tar RZ In20": 9,
    "Fantasy Pts": 72,
    "RZ Opp In5": 5,
    "Rush Yds": 147,
    "url": "https://www.rotowire.com/football/redzonestats.htm?pos=TM&season=2017&range=Week4",
    "Tar RZ In10": 4,
    "Rush TD": 1,
    "RZ Opp In20": 15,
    "Col Teamname": "Atlanta Falcons",
    "RZ Opp In10": 9
  },
  "Baltimore Ravens": {
    "Att": 15,
    "Rec": 31,
    "Rec Yds": 235,
    "Rec TD": 1,
    "Rush RZ In20": 0,
    "Rush RZ In5": 0,
    "Tar RZ In5": 2,
    "Fantasy Pts/G": 56.5,
    "Rush RZ In10": 0,
    "Tar RZ In20": 7,
    "Fantasy Pts": 56,
    "RZ Opp In5": 2,
    "Rush Yds": 82,
    "url": "https://www.rotowire.com/football/redzonestats.htm?pos=TM&season=2017&range=Week4",
    "Tar RZ In10": 2,
    "Rush TD": 0,
    "RZ Opp In20": 7,
    "Col Teamname": "Baltimore Ravens",
    "RZ Opp In10": 2
  },
  "Buffalo Bills": {
    "Att": 36,
    "Rec": 12,
    "Rec Yds": 182,
    "Rec TD": 1,
    "Rush RZ In20": 4,
    "Rush RZ In5": 1,
    "Tar RZ In5": 1,
    "Fantasy Pts/G": 60,
    "Rush RZ In10": 2,
    "Tar RZ In20": 3,
    "Fantasy Pts": 60,
    "RZ Opp In5": 2,
    "Rush Yds": 117,
    "url": "https://www.rotowire.com/football/redzonestats.htm?pos=TM&season=2017&range=Week4",
    "Tar RZ In10": 2,
    "Rush TD": 0,
    "RZ Opp In20": 7,
    "Col Teamname": "Buffalo Bills",
    "RZ Opp In10": 4
  },
  "Carolina Panthers": {
    "Att": 29,
    "Rec": 22,
    "Rec Yds": 316,
    "Rec TD": 3,
    "Rush RZ In20": 5,
    "Rush RZ In5": 0,
    "Tar RZ In5": 0,
    "Fantasy Pts/G": 106.4,
    "Rush RZ In10": 1,
    "Tar RZ In20": 4,
    "Fantasy Pts": 106,
    "RZ Opp In5": 0,
    "Rush Yds": 140,
    "url": "https://www.rotowire.com/football/redzonestats.htm?pos=TM&season=2017&range=Week4",
    "Tar RZ In10": 1,
    "Rush TD": 1,
    "RZ Opp In20": 9,
    "Col Teamname": "Carolina Panthers",
    "RZ Opp In10": 2
  },
  "Chicago Bears": {
    "Att": 30,
    "Rec": 21,
    "Rec Yds": 218,
    "Rec TD": 1,
    "Rush RZ In20": 2,
    "Rush RZ In5": 1,
    "Tar RZ In5": 1,
    "Fantasy Pts/G": 61,
    "Rush RZ In10": 2,
    "Tar RZ In20": 6,
    "Fantasy Pts": 61,
    "RZ Opp In5": 2,
    "Rush Yds": 103,
    "url": "https://www.rotowire.com/football/redzonestats.htm?pos=TM&season=2017&range=Week4",
    "Tar RZ In10": 1,
    "Rush TD": 1,
    "RZ Opp In20": 8,
    "Col Teamname": "Chicago Bears",
    "RZ Opp In10": 3
  },
  "Cincinnati Bengals": {
    "Att": 30,
    "Rec": 25,
    "Rec Yds": 286,
    "Rec TD": 4,
    "Rush RZ In20": 4,
    "Rush RZ In5": 1,
    "Tar RZ In5": 1,
    "Fantasy Pts/G": 98.5,
    "Rush RZ In10": 1,
    "Tar RZ In20": 4,
    "Fantasy Pts": 99,
    "RZ Opp In5": 2,
    "Rush Yds": 86,
    "url": "https://www.rotowire.com/football/redzonestats.htm?pos=TM&season=2017&range=Week4",
    "Tar RZ In10": 3,
    "Rush TD": 0,
    "RZ Opp In20": 8,
    "Col Teamname": "Cincinnati Bengals",
    "RZ Opp In10": 4
  },
  "Cleveland Browns": {
    "Att": 17,
    "Rec": 21,
    "Rec Yds": 183,
    "Rec TD": 0,
    "Rush RZ In20": 4,
    "Rush RZ In5": 2,
    "Tar RZ In5": 0,
    "Fantasy Pts/G": 39,
    "Rush RZ In10": 3,
    "Tar RZ In20": 4,
    "Fantasy Pts": 39,
    "RZ Opp In5": 2,
    "Rush Yds": 45,
    "url": "https://www.rotowire.com/football/redzonestats.htm?pos=TM&season=2017&range=Week4",
    "Tar RZ In10": 2,
    "Rush TD": 1,
    "RZ Opp In20": 8,
    "Col Teamname": "Cleveland Browns",
    "RZ Opp In10": 5
  },
  "Dallas Cowboys": {
    "Att": 27,
    "Rec": 20,
    "Rec Yds": 252,
    "Rec TD": 3,
    "Rush RZ In20": 6,
    "Rush RZ In5": 3,
    "Tar RZ In5": 0,
    "Fantasy Pts/G": 98.7,
    "Rush RZ In10": 3,
    "Tar RZ In20": 4,
    "Fantasy Pts": 99,
    "RZ Opp In5": 3,
    "Rush Yds": 189,
    "url": "https://www.rotowire.com/football/redzonestats.htm?pos=TM&season=2017&range=Week4",
    "Tar RZ In10": 2,
    "Rush TD": 1,
    "RZ Opp In20": 10,
    "Col Teamname": "Dallas Cowboys",
    "RZ Opp In10": 5
  },
  "Denver Broncos": {
    "Att": 32,
    "Rec": 16,
    "Rec Yds": 179,
    "Rec TD": 1,
    "Rush RZ In20": 4,
    "Rush RZ In5": 0,
    "Tar RZ In5": 1,
    "Fantasy Pts/G": 61.2,
    "Rush RZ In10": 1,
    "Tar RZ In20": 5,
    "Fantasy Pts": 61,
    "RZ Opp In5": 1,
    "Rush Yds": 143,
    "url": "https://www.rotowire.com/football/redzonestats.htm?pos=TM&season=2017&range=Week4",
    "Tar RZ In10": 2,
    "Rush TD": 0,
    "RZ Opp In20": 9,
    "Col Teamname": "Denver Broncos",
    "RZ Opp In10": 3
  },
  "Detroit Lions": {
    "Att": 31,
    "Rec": 19,
    "Rec Yds": 209,
    "Rec TD": 0,
    "Rush RZ In20": 3,
    "Rush RZ In5": 1,
    "Tar RZ In5": 1,
    "Fantasy Pts/G": 53.1,
    "Rush RZ In10": 1,
    "Tar RZ In20": 5,
    "Fantasy Pts": 53,
    "RZ Opp In5": 2,
    "Rush Yds": 97,
    "url": "https://www.rotowire.com/football/redzonestats.htm?pos=TM&season=2017&range=Week4",
    "Tar RZ In10": 1,
    "Rush TD": 1,
    "RZ Opp In20": 8,
    "Col Teamname": "Detroit Lions",
    "RZ Opp In10": 2
  },
  "Green Bay Packers": {
    "Att": 24,
    "Rec": 19,
    "Rec Yds": 179,
    "Rec TD": 4,
    "Rush RZ In20": 5,
    "Rush RZ In5": 2,
    "Tar RZ In5": 5,
    "Fantasy Pts/G": 87,
    "Rush RZ In10": 4,
    "Tar RZ In20": 9,
    "Fantasy Pts": 87,
    "RZ Opp In5": 7,
    "Rush Yds": 91,
    "url": "https://www.rotowire.com/football/redzonestats.htm?pos=TM&season=2017&range=Week4",
    "Tar RZ In10": 8,
    "Rush TD": 1,
    "RZ Opp In20": 14,
    "Col Teamname": "Green Bay Packers",
    "RZ Opp In10": 12
  },
  "Houston Texans": {
    "Att": 42,
    "Rec": 25,
    "Rec Yds": 283,
    "Rec TD": 4,
    "Rush RZ In20": 8,
    "Rush RZ In5": 3,
    "Tar RZ In5": 0,
    "Fantasy Pts/G": 126.8,
    "Rush RZ In10": 5,
    "Tar RZ In20": 6,
    "Fantasy Pts": 127,
    "RZ Opp In5": 3,
    "Rush Yds": 173,
    "url": "https://www.rotowire.com/football/redzonestats.htm?pos=TM&season=2017&range=Week4",
    "Tar RZ In10": 3,
    "Rush TD": 2,
    "RZ Opp In20": 14,
    "Col Teamname": "Houston Texans",
    "RZ Opp In10": 8
  },
  "Indianapolis Colts": {
    "Att": 25,
    "Rec": 16,
    "Rec Yds": 157,
    "Rec TD": 1,
    "Rush RZ In20": 3,
    "Rush RZ In5": 2,
    "Tar RZ In5": 0,
    "Fantasy Pts/G": 53.4,
    "Rush RZ In10": 2,
    "Tar RZ In20": 2,
    "Fantasy Pts": 53,
    "RZ Opp In5": 2,
    "Rush Yds": 98,
    "url": "https://www.rotowire.com/football/redzonestats.htm?pos=TM&season=2017&range=Week4",
    "Tar RZ In10": 1,
    "Rush TD": 1,
    "RZ Opp In20": 5,
    "Col Teamname": "Indianapolis Colts",
    "RZ Opp In10": 3
  },
  "Jacksonville Jaguars": {
    "Att": 39,
    "Rec": 15,
    "Rec Yds": 140,
    "Rec TD": 1,
    "Rush RZ In20": 2,
    "Rush RZ In5": 0,
    "Tar RZ In5": 1,
    "Fantasy Pts/G": 56.5,
    "Rush RZ In10": 0,
    "Tar RZ In20": 6,
    "Fantasy Pts": 57,
    "RZ Opp In5": 1,
    "Rush Yds": 175,
    "url": "https://www.rotowire.com/football/redzonestats.htm?pos=TM&season=2017&range=Week4",
    "Tar RZ In10": 4,
    "Rush TD": 0,
    "RZ Opp In20": 8,
    "Col Teamname": "Jacksonville Jaguars",
    "RZ Opp In10": 4
  },
  "Kansas City Chiefs": {
    "Att": 31,
    "Rec": 27,
    "Rec Yds": 293,
    "Rec TD": 1,
    "Rush RZ In20": 6,
    "Rush RZ In5": 2,
    "Tar RZ In5": 0,
    "Fantasy Pts/G": 87.8,
    "Rush RZ In10": 3,
    "Tar RZ In20": 3,
    "Fantasy Pts": 88,
    "RZ Opp In5": 2,
    "Rush Yds": 168,
    "url": "https://www.rotowire.com/football/redzonestats.htm?pos=TM&season=2017&range=Week4",
    "Tar RZ In10": 0,
    "Rush TD": 1,
    "RZ Opp In20": 9,
    "Col Teamname": "Kansas City Chiefs",
    "RZ Opp In10": 3
  },
  "Los Angeles Chargers": {
    "Att": 13,
    "Rec": 22,
    "Rec Yds": 347,
    "Rec TD": 2,
    "Rush RZ In20": 0,
    "Rush RZ In5": 0,
    "Tar RZ In5": 2,
    "Fantasy Pts/G": 89.9,
    "Rush RZ In10": 0,
    "Tar RZ In20": 6,
    "Fantasy Pts": 90,
    "RZ Opp In5": 2,
    "Rush Yds": 58,
    "url": "https://www.rotowire.com/football/redzonestats.htm?pos=TM&season=2017&range=Week4",
    "Tar RZ In10": 3,
    "Rush TD": 1,
    "RZ Opp In20": 6,
    "Col Teamname": "Los Angeles Chargers",
    "RZ Opp In10": 3
  },
  "Los Angeles Rams": {
    "Att": 31,
    "Rec": 21,
    "Rec Yds": 255,
    "Rec TD": 2,
    "Rush RZ In20": 3,
    "Rush RZ In5": 0,
    "Tar RZ In5": 0,
    "Fantasy Pts/G": 98.1,
    "Rush RZ In10": 1,
    "Tar RZ In20": 8,
    "Fantasy Pts": 98,
    "RZ Opp In5": 0,
    "Rush Yds": 168,
    "url": "https://www.rotowire.com/football/redzonestats.htm?pos=TM&season=2017&range=Week4",
    "Tar RZ In10": 5,
    "Rush TD": 0,
    "RZ Opp In20": 11,
    "Col Teamname": "Los Angeles Rams",
    "RZ Opp In10": 6
  },
  "Miami Dolphins": {
    "Att": 15,
    "Rec": 20,
    "Rec Yds": 164,
    "Rec TD": 0,
    "Rush RZ In20": 0,
    "Rush RZ In5": 0,
    "Tar RZ In5": 1,
    "Fantasy Pts/G": 30.4,
    "Rush RZ In10": 0,
    "Tar RZ In20": 1,
    "Fantasy Pts": 30,
    "RZ Opp In5": 1,
    "Rush Yds": 58,
    "url": "https://www.rotowire.com/football/redzonestats.htm?pos=TM&season=2017&range=Week4",
    "Tar RZ In10": 1,
    "Rush TD": 0,
    "RZ Opp In20": 1,
    "Col Teamname": "Miami Dolphins",
    "RZ Opp In10": 1
  },
  "Minnesota Vikings": {
    "Att": 22,
    "Rec": 16,
    "Rec Yds": 219,
    "Rec TD": 0,
    "Rush RZ In20": 4,
    "Rush RZ In5": 2,
    "Tar RZ In5": 0,
    "Fantasy Pts/G": 48.6,
    "Rush RZ In10": 4,
    "Tar RZ In20": 1,
    "Fantasy Pts": 49,
    "RZ Opp In5": 2,
    "Rush Yds": 87,
    "url": "https://www.rotowire.com/football/redzonestats.htm?pos=TM&season=2017&range=Week4",
    "Tar RZ In10": 0,
    "Rush TD": 1,
    "RZ Opp In20": 5,
    "Col Teamname": "Minnesota Vikings",
    "RZ Opp In10": 4
  },
  "New England Patriots": {
    "Att": 19,
    "Rec": 32,
    "Rec Yds": 307,
    "Rec TD": 2,
    "Rush RZ In20": 6,
    "Rush RZ In5": 1,
    "Tar RZ In5": 4,
    "Fantasy Pts/G": 92.1,
    "Rush RZ In10": 5,
    "Tar RZ In20": 9,
    "Fantasy Pts": 92,
    "RZ Opp In5": 5,
    "Rush Yds": 80,
    "url": "https://www.rotowire.com/football/redzonestats.htm?pos=TM&season=2017&range=Week4",
    "Tar RZ In10": 4,
    "Rush TD": 1,
    "RZ Opp In20": 15,
    "Col Teamname": "New England Patriots",
    "RZ Opp In10": 9
  },
  "New Orleans Saints": {
    "Att": 28,
    "Rec": 29,
    "Rec Yds": 268,
    "Rec TD": 2,
    "Rush RZ In20": 5,
    "Rush RZ In5": 0,
    "Tar RZ In5": 1,
    "Fantasy Pts/G": 76.8,
    "Rush RZ In10": 1,
    "Tar RZ In20": 7,
    "Fantasy Pts": 77,
    "RZ Opp In5": 1,
    "Rush Yds": 86,
    "url": "https://www.rotowire.com/football/redzonestats.htm?pos=TM&season=2017&range=Week4",
    "Tar RZ In10": 2,
    "Rush TD": 0,
    "RZ Opp In20": 12,
    "Col Teamname": "New Orleans Saints",
    "RZ Opp In10": 3
  },
  "New York Giants": {
    "Att": 28,
    "Rec": 30,
    "Rec Yds": 288,
    "Rec TD": 2,
    "Rush RZ In20": 9,
    "Rush RZ In5": 2,
    "Tar RZ In5": 2,
    "Fantasy Pts/G": 83.3,
    "Rush RZ In10": 4,
    "Tar RZ In20": 4,
    "Fantasy Pts": 83,
    "RZ Opp In5": 4,
    "Rush Yds": 91,
    "url": "https://www.rotowire.com/football/redzonestats.htm?pos=TM&season=2017&range=Week4",
    "Tar RZ In10": 2,
    "Rush TD": 1,
    "RZ Opp In20": 13,
    "Col Teamname": "New York Giants",
    "RZ Opp In10": 6
  },
  "New York Jets": {
    "Att": 32,
    "Rec": 23,
    "Rec Yds": 255,
    "Rec TD": 0,
    "Rush RZ In20": 2,
    "Rush RZ In5": 0,
    "Tar RZ In5": 0,
    "Fantasy Pts/G": 86.9,
    "Rush RZ In10": 1,
    "Tar RZ In20": 2,
    "Fantasy Pts": 87,
    "RZ Opp In5": 0,
    "Rush Yds": 256,
    "url": "https://www.rotowire.com/football/redzonestats.htm?pos=TM&season=2017&range=Week4",
    "Tar RZ In10": 2,
    "Rush TD": 2,
    "RZ Opp In20": 4,
    "Col Teamname": "New York Jets",
    "RZ Opp In10": 3
  },
  "Oakland Raiders": {
    "Att": 15,
    "Rec": 21,
    "Rec Yds": 249,
    "Rec TD": 1,
    "Rush RZ In20": 0,
    "Rush RZ In5": 0,
    "Tar RZ In5": 0,
    "Fantasy Pts/G": 53.8,
    "Rush RZ In10": 0,
    "Tar RZ In20": 3,
    "Fantasy Pts": 54,
    "RZ Opp In5": 0,
    "Rush Yds": 24,
    "url": "https://www.rotowire.com/football/redzonestats.htm?pos=TM&season=2017&range=Week4",
    "Tar RZ In10": 0,
    "Rush TD": 0,
    "RZ Opp In20": 3,
    "Col Teamname": "Oakland Raiders",
    "RZ Opp In10": 0
  },
  "Philadelphia Eagles": {
    "Att": 42,
    "Rec": 17,
    "Rec Yds": 242,
    "Rec TD": 1,
    "Rush RZ In20": 7,
    "Rush RZ In5": 5,
    "Tar RZ In5": 1,
    "Fantasy Pts/G": 87.7,
    "Rush RZ In10": 5,
    "Tar RZ In20": 2,
    "Fantasy Pts": 88,
    "RZ Opp In5": 6,
    "Rush Yds": 214,
    "url": "https://www.rotowire.com/football/redzonestats.htm?pos=TM&season=2017&range=Week4",
    "Tar RZ In10": 2,
    "Rush TD": 1,
    "RZ Opp In20": 9,
    "Col Teamname": "Philadelphia Eagles",
    "RZ Opp In10": 7
  },
  "Pittsburgh Steelers": {
    "Att": 42,
    "Rec": 18,
    "Rec Yds": 216,
    "Rec TD": 1,
    "Rush RZ In20": 10,
    "Rush RZ In5": 2,
    "Tar RZ In5": 0,
    "Fantasy Pts/G": 79.7,
    "Rush RZ In10": 3,
    "Tar RZ In20": 3,
    "Fantasy Pts": 80,
    "RZ Opp In5": 2,
    "Rush Yds": 173,
    "url": "https://www.rotowire.com/football/redzonestats.htm?pos=TM&season=2017&range=Week4",
    "Tar RZ In10": 1,
    "Rush TD": 2,
    "RZ Opp In20": 13,
    "Col Teamname": "Pittsburgh Steelers",
    "RZ Opp In10": 4
  },
  "Seattle Seahawks": {
    "Att": 33,
    "Rec": 21,
    "Rec Yds": 295,
    "Rec TD": 2,
    "Rush RZ In20": 1,
    "Rush RZ In5": 0,
    "Tar RZ In5": 0,
    "Fantasy Pts/G": 103.7,
    "Rush RZ In10": 1,
    "Tar RZ In20": 2,
    "Fantasy Pts": 104,
    "RZ Opp In5": 0,
    "Rush Yds": 194,
    "url": "https://www.rotowire.com/football/redzonestats.htm?pos=TM&season=2017&range=Week4",
    "Tar RZ In10": 1,
    "Rush TD": 2,
    "RZ Opp In20": 3,
    "Col Teamname": "Seattle Seahawks",
    "RZ Opp In10": 2
  },
  "San Francisco 49ers": {
    "Att": 27,
    "Rec": 24,
    "Rec Yds": 234,
    "Rec TD": 0,
    "Rush RZ In20": 4,
    "Rush RZ In5": 0,
    "Tar RZ In5": 0,
    "Fantasy Pts/G": 59.6,
    "Rush RZ In10": 1,
    "Tar RZ In20": 2,
    "Fantasy Pts": 60,
    "RZ Opp In5": 0,
    "Rush Yds": 95,
    "url": "https://www.rotowire.com/football/redzonestats.htm?pos=TM&season=2017&range=Week4",
    "Tar RZ In10": 0,
    "Rush TD": 0,
    "RZ Opp In20": 6,
    "Col Teamname": "San Francisco 49ers",
    "RZ Opp In10": 1
  },
  "Tampa Bay Buccaneers": {
    "Att": 23,
    "Rec": 22,
    "Rec Yds": 332,
    "Rec TD": 3,
    "Rush RZ In20": 3,
    "Rush RZ In5": 1,
    "Tar RZ In5": 2,
    "Fantasy Pts/G": 97.9,
    "Rush RZ In10": 1,
    "Tar RZ In20": 4,
    "Fantasy Pts": 98,
    "RZ Opp In5": 3,
    "Rush Yds": 111,
    "url": "https://www.rotowire.com/football/redzonestats.htm?pos=TM&season=2017&range=Week4",
    "Tar RZ In10": 3,
    "Rush TD": 0,
    "RZ Opp In20": 7,
    "Col Teamname": "Tampa Bay Buccaneers",
    "RZ Opp In10": 4
  },
  "Tennessee Titans": {
    "Att": 19,
    "Rec": 10,
    "Rec Yds": 117,
    "Rec TD": 0,
    "Rush RZ In20": 1,
    "Rush RZ In5": 1,
    "Tar RZ In5": 0,
    "Fantasy Pts/G": 40.2,
    "Rush RZ In10": 1,
    "Tar RZ In20": 0,
    "Fantasy Pts": 40,
    "RZ Opp In5": 1,
    "Rush Yds": 86,
    "url": "https://www.rotowire.com/football/redzonestats.htm?pos=TM&season=2017&range=Week4",
    "Tar RZ In10": 0,
    "Rush TD": 2,
    "RZ Opp In20": 1,
    "Col Teamname": "Tennessee Titans",
    "RZ Opp In10": 1
  },
  "Washington Redskins": {
    "Att": 26,
    "Rec": 14,
    "Rec Yds": 220,
    "Rec TD": 2,
    "Rush RZ In20": 4,
    "Rush RZ In5": 2,
    "Tar RZ In5": 1,
    "Fantasy Pts/G": 72.1,
    "Rush RZ In10": 4,
    "Tar RZ In20": 1,
    "Fantasy Pts": 72,
    "RZ Opp In5": 3,
    "Rush Yds": 111,
    "url": "https://www.rotowire.com/football/redzonestats.htm?pos=TM&season=2017&range=Week4",
    "Tar RZ In10": 1,
    "Rush TD": 0,
    "RZ Opp In20": 5,
    "Col Teamname": "Washington Redskins",
    "RZ Opp In10": 5
  }
}